glurpc/REFERENCE_LOGIC.md
glurpc/__init__.py
glurpc/app.py
glurpc/cache.py
glurpc/config.py
glurpc/core.py
glurpc/data_classes.py
glurpc/engine.py
glurpc/logic.py
glurpc/middleware.py
glurpc/schemas.py
glurpc/state.py
service/__init__.py
service/combined_service.py
service/common.py
service/glurpc_service.py
service/service_spec/.gitignore
service/service_spec/glurpc.proto
service/service_spec/glurpc_pb2.py
service/service_spec/glurpc_pb2_grpc.py
glurpc-0.6.3.dist-info/METADATA
glurpc-0.6.3.dist-info/WHEEL
glurpc-0.6.3.dist-info/entry_points.txt
glurpc-0.6.3.dist-info/licenses/LICENSE
glurpc-0.6.3.dist-info/RECORD
