Metadata-Version: 2.4
Name: glurpc
Version: 0.6.3
Summary: gRPC and REST endpoint for glucose prediction inference
Author-email: Newton Winter <isoutthere@gmail.com>
Maintainer-email: Anton Kulaga <antonkulaga@gmail.com>, Newton Winter <isoutthere@gmail.com>
License: MIT License
License-File: LICENSE
Requires-Python: >=3.11
Requires-Dist: aiorwlock>=1.5.0
Requires-Dist: cachetools>=6.2.2
Requires-Dist: cgm-format>=0.7.0
Requires-Dist: darts==0.29.0
Requires-Dist: diskcache>=5.6.3
Requires-Dist: fastapi>=0.123.0
Requires-Dist: glucosedao-glucobench>=0.4.1
Requires-Dist: grpcio-tools>=1.76.0
Requires-Dist: grpcio>=1.76.0
Requires-Dist: huggingface-hub>=0.36.0
Requires-Dist: kaleido==0.2.1
Requires-Dist: numpydantic>=1.7.0
Requires-Dist: plotly<6.0
Requires-Dist: polars>=1.35.2
Requires-Dist: pydantic<3.0
Requires-Dist: python-multipart
Requires-Dist: typer>=0.9.0
Requires-Dist: uvicorn>=0.38.0
Provides-Extra: dev
Requires-Dist: httpx>=0.27.0; extra == 'dev'
Requires-Dist: pytest-asyncio>=1.3.0; extra == 'dev'
Requires-Dist: pytest>=8.0.0; extra == 'dev'
Requires-Dist: snet-cli>=0.1.2; extra == 'dev'
